llama_index/py.typed
llama_index/vector_stores/postgres/__init__.py
llama_index/vector_stores/postgres/base.py
llama_index_vector_stores_postgres-0.7.1.dist-info/METADATA
llama_index_vector_stores_postgres-0.7.1.dist-info/WHEEL
llama_index_vector_stores_postgres-0.7.1.dist-info/licenses/LICENSE
llama_index_vector_stores_postgres-0.7.1.dist-info/RECORD
