Metadata-Version: 2.4
Name: llama-index-vector-stores-postgres
Version: 0.7.1
Summary: llama-index vector_stores postgres integration
Author-email: Your Name <you@example.com>
License-Expression: MIT
License-File: LICENSE
Requires-Python: <4.0,>=3.9
Requires-Dist: asyncpg<1.0.0,>=0.29.0
Requires-Dist: llama-index-core<0.15,>=0.13.0
Requires-Dist: pgvector<1.0.0,>=0.3.6
Requires-Dist: psycopg2-binary<3.0.0,>=2.9.9
Requires-Dist: sqlalchemy[asyncio]<2.1,>=1.4.49
